{
  "common": {
    "term_truecolor": false
  },
  "segments": {
    "right": [
      {
        "function": "powerline.segments.common.players.rhythmbox",
        "name": "player",
        "args": {
          "format": "{state_symbol} {title} [{elapsed}/{total}]"
        }
      },
      {
        "function": "powerline.segments.common.players.cmus",
        "name": "player",
        "args": {
          "format": "{state_symbol} {title} [{elapsed}/{total}]"
        }
      },
      {
        "function": "powerline.segments.common.net.network_load",
        "args": {
          "recv_format": "{value:>8}⬇",
          "sent_format": "{value:>8}⬆"
        }
      },
      {
        "function": "powerline.segments.common.time.date",
        "name": "time",
        "args": {
          "format": "%m/%d %H:%M:%S",
          "istime": true
        }
      },
      {
        "function": "powerline.segments.common.bat.battery",
        "args": {
          "full_heart": "♥",
          "empty_heart": "♡",
          "online": "⚡︎",
          "offline": "☕"
        }
      },
      {
        "function": "powerline.segments.common.net.hostname"
      }
    ]
  }
}
