{
  // coc specific
  "suggest.virtualText": true,
  "notification.border": false,
  "diagnostic.virtualText": true,
  "diagnostic.virtualTextLevel": "hint",
  "diagnostic.hintSign": "⏵",
  "diagnostic.infoSign": "ℹ",
  "diagnostic.errorSign": "♺", // "⊘",
  "diagnostic.warningSign": "⚠",
  "diagnostic.virtualTextCurrentLineOnly": false,
  "notification.focusable": false,
  "notification.winblend": 0,
  "codeLens.enable": true,

  // rust
  "rust-analyzer.workspace.symbol.search.scope": "workspace_and_dependencies",
  "rust-analyzer.debug.runtime": "vimspector",
  "rust-analyzer.workspace.symbol.search.limit": 256,
  "rust-analyzer.lru.capacity": 256,
  "rust-analyzer.typing.autoClosingAngleBrackets.enable": true,
  "rust-analyzer.imports.granularity.enforce": true,
  "rust-analyzer.completion.postfix.enable": true,
  "rust-analyzer.completion.autoself.enable": true,
  "rust-analyzer.completion.autoimport.enable": true,
  "rust-analyzer.restartServerOnConfigChange":  true,
  "rust-analyzer.lens.enable": true,
  "rust-analyzer.checkOnSave.command": "clippy",

  // Go
  "go.goplsUseDaemon": true
}
